airnow/__init__.py
airnow/airnow.py
airnow/models.py
airnow/utils.py
python_airnow-0.1.1.dist-info/LICENSE.md
python_airnow-0.1.1.dist-info/WHEEL
python_airnow-0.1.1.dist-info/METADATA
python_airnow-0.1.1.dist-info/RECORD
