Metadata-Version: 2.1
Name: python-airnow
Version: 0.1.1
Summary: A simple wrapper around the AirNow API
License: MIT
Author: Ronnie Llamado
Author-email: llamado.ronnie@gmail.com
Requires-Python: >=3.7,<4.0
Classifier: License :: OSI Approved :: MIT License
Classifier: Programming Language :: Python :: 3
Classifier: Programming Language :: Python :: 3.7
Classifier: Programming Language :: Python :: 3.8
Classifier: Programming Language :: Python :: 3.9
Requires-Dist: python-dateutil (>=2.8.2,<3.0.0)
Requires-Dist: requests (>=2.26.0,<3.0.0)
